odoo9_addon_quality_control_team-9.0.1.0.0.99.dev3-nspkg.pth
odoo_addons/quality_control_team/README.rst
odoo_addons/quality_control_team/__init__.py
odoo_addons/quality_control_team/__openerp__.py
odoo_addons/quality_control_team/data/quality_control_team_data.xml
odoo_addons/quality_control_team/i18n/quality_control_team.pot
odoo_addons/quality_control_team/models/__init__.py
odoo_addons/quality_control_team/models/qc_team.py
odoo_addons/quality_control_team/models/res_partner.py
odoo_addons/quality_control_team/models/res_user.py
odoo_addons/quality_control_team/security/ir.model.access.csv
odoo_addons/quality_control_team/static/description/icon.png
odoo_addons/quality_control_team/static/description/icon.svg
odoo_addons/quality_control_team/tests/__init__.py
odoo_addons/quality_control_team/tests/test_quality_control_team.py
odoo_addons/quality_control_team/views/qc_team_dashboard.xml
odoo_addons/quality_control_team/views/qc_team_view.xml
odoo9_addon_quality_control_team-9.0.1.0.0.99.dev3.dist-info/METADATA
odoo9_addon_quality_control_team-9.0.1.0.0.99.dev3.dist-info/WHEEL
odoo9_addon_quality_control_team-9.0.1.0.0.99.dev3.dist-info/namespace_packages.txt
odoo9_addon_quality_control_team-9.0.1.0.0.99.dev3.dist-info/top_level.txt
odoo9_addon_quality_control_team-9.0.1.0.0.99.dev3.dist-info/RECORD
